rstviewer/__init__.py
rstviewer/rstviewer.py
rstviewer-0.0.4.1.dist-info/DESCRIPTION.rst
rstviewer-0.0.4.1.dist-info/METADATA
rstviewer-0.0.4.1.dist-info/RECORD
rstviewer-0.0.4.1.dist-info/WHEEL
rstviewer-0.0.4.1.dist-info/entry_points.txt
rstviewer-0.0.4.1.dist-info/metadata.json
rstviewer-0.0.4.1.dist-info/top_level.txt
