Metadata-Version: 2.0
Name: rstviewer
Version: 0.0.4.1
Summary: An in-browser RST viewer with live updating
Home-page: https://github.com/terhorst/rstviewer
Author: Jonathan Terhorst
Author-email: terhorst@gmail.com
License: GPL
Keywords: reStructuredText rst editor viewer
Platform: UNKNOWN
Requires-Dist: rst2html5
Requires-Dist: hachiko
Requires-Dist: watchdog
Requires-Dist: aiohttp
